dl_01/Q1_and_or.py
dl_01/Q2_xor_andnot.py
dl_01/Q3_hebbian_net.py
dl_01/Q4_discrete_hopfield_net.py
dl_01/Q5_Kohonen_self_organizing_maps.py
dl_01/__init__.py
dl_01/main.py
dl_01-3.dist-info/LICENSE
dl_01-3.dist-info/METADATA
dl_01-3.dist-info/WHEEL
dl_01-3.dist-info/top_level.txt
dl_01-3.dist-info/RECORD
